[{"i": "b23e1572", "w": "D", "u": "8-concord-zion-roots", "s": "tokyo-starfish-923-se-3rd-street", "m": "R", "a": "923 SE 3rd St Bend, OR", "b": "Zion Roots", "n": "$8 - Concord - Zion Roots", "t": "I", "p": "flower-stock-4-v1.jpg", "%": 24.8, "cbd": 0.0, "tac": 0, "c": [{"g": 1.0, "$": 8}, {"g": 2.0, "$": 16}, {"g": 3.5, "$": 27}, {"g": 7.0, "$": 50}, {"g": 14.0, "$": 100}, {"g": 28.0, "$": 190}]}, {"i": "b56974ff", "w": "D", "u": "11-tokyo-purple-ice-water", "s": "tokyo-starfish-923-se-3rd-street", "m": "R", "a": "923 SE 3rd St Bend, OR", "b": "Tokyo Starfish", "n": "$11 - Tokyo - Purple Ice Water", "t": "H", "p": "f35aa1f82a21df964831370eadf99d40", "%": 25.2, "cbd": 0.1, "tac": 0, "c": [{"g": 1.0, "$": 11}, {"g": 2.0, "$": 22}, {"g": 3.5, "$": 37}, {"g": 7.0, "$": 69}, {"g": 14.0, "$": 138}, {"g": 28.0, "$": 262}]}, {"i": "a90b2016", "w": "D", "u": "13-highway-101-oca", "s": "tokyo-starfish-923-se-3rd-street", "m": "R", "a": "923 SE 3rd St Bend, OR", "b": "Oregon Cannabis Authority", "n": "$13 - Highway 101 - OCA", "t": "S", "p": "flower-stock-8-v1.jpg", "%": 25.7, "cbd": 0, "tac": 0, "c": [{"g": 1.0, "$": 13}, {"g": 2.0, "$": 26}, {"g": 3.5, "$": 43}, {"g": 7.0, "$": 82}, {"g": 14.0, "$": 164}, {"g": 28.0, "$": 309}]}, {"i": "1fc25370", "w": "D", "u": "pre-pack-tokyo-chem-chillz", "s": "tokyo-starfish-923-se-3rd-street", "m": "R", "a": "923 SE 3rd St Bend, OR", "b": "Tokyo Starfish", "n": "Pre Pack - Tokyo - Chem Chillz", "t": "I", "p": "b9d1c87b74de75385021df92173c97a1", "%": 25.7, "cbd": 0.1, "tac": 0, "c": [{"g": 28.0, "$": 100}]}, {"i": "e978d1ad", "w": "D", "u": "10-blackberry-moonshine-cannassentials", "s": "tokyo-starfish-923-se-3rd-street", "m": "R", "a": "923 SE 3rd St Bend, OR", "b": "Cannassentials", "n": "$10 - Blackberry Moonshine - Cannassentials", "t": "I", "p": "flower-stock-11-v1.jpg", "%": 20.5, "cbd": 0, "tac": 0, "c": [{"g": 1.0, "$": 10}, {"g": 2.0, "$": 20}, {"g": 3.5, "$": 33}, {"g": 7.0, "$": 63}, {"g": 14.0, "$": 126}, {"g": 28.0, "$": 238}]}, {"i": "1eb3edbc", "w": "D", "u": "8-quantum-kush-the-cannabis-farm", "s": "tokyo-starfish-923-se-3rd-street", "m": "R", "a": "923 SE 3rd St Bend, OR", "b": "The Cannabis Farm", "n": "$8 - Quantum Kush - The Cannabis Farm", "t": "S", "p": "flower-stock-14-v1.jpg", "%": 27.1, "cbd": 0.1, "tac": 0, "c": [{"g": 1.0, "$": 8}, {"g": 2.0, "$": 16}, {"g": 3.5, "$": 27}, {"g": 7.0, "$": 50}, {"g": 14.0, "$": 100}, {"g": 28.0, "$": 190}]}, {"i": "c654471d", "w": "D", "u": "12-god-indo-supply", "s": "tokyo-starfish-923-se-3rd-street", "m": "R", "a": "923 SE 3rd St Bend, OR", "b": "Indo Supply Co.", "n": "$12 - God - Indo Supply", "t": "I", "p": "flower-stock-9-v1.jpg", "%": 17.4, "cbd": 0, "tac": 0, "c": [{"g": 1.0, "$": 12}, {"g": 2.0, "$": 24}, {"g": 3.5, "$": 40}, {"g": 7.0, "$": 76}, {"g": 14.0, "$": 152}, {"g": 28.0, "$": 286}]}, {"i": "07a1b3a3", "w": "D", "u": "5-hindu-dakini-alter", "s": "tokyo-starfish-923-se-3rd-street", "m": "R", "a": "923 SE 3rd St Bend, OR", "b": "Alter Farms", "n": "$5 - Hindu Dakini - Alter", "t": "I", "p": "d0685184f9766f24de9bf6ccf8e7223e", "%": 26.0, "cbd": 0.1, "tac": 0, "c": [{"g": 1.0, "$": 5}, {"g": 2.0, "$": 10}, {"g": 3.5, "$": 17}, {"g": 7.0, "$": 32}, {"g": 14.0, "$": 64}, {"g": 28.0, "$": 119}]}, {"i": "c926f8d6", "w": "D", "u": "13-vanilla-gorilla-deep-creek", "s": "tokyo-starfish-923-se-3rd-street", "m": "R", "a": "923 SE 3rd St Bend, OR", "b": "Deep Creek Gardens", "n": "$13 - Vanilla Gorilla - Deep Creek", "t": "I", "p": "ce3bcedc00a6ca8473d4cd4cc395cf77", "%": 29.0, "cbd": 0.1, "tac": 0, "c": [{"g": 1.0, "$": 13}, {"g": 2.0, "$": 26}]}, {"i": "40752de7", "w": "D", "u": "16-meat-breath-white-wolf", "s": "tokyo-starfish-923-se-3rd-street", "m": "R", "a": "923 SE 3rd St Bend, OR", "b": "White Wolf", "n": "$16 - Meat Breath - White Wolf", "t": "I", "p": "flower-stock-11-v1.jpg", "%": 24.7, "cbd": 0, "tac": 0, "c": [{"g": 1.0, "$": 16}, {"g": 2.0, "$": 32}, {"g": 3.5, "$": 53}, {"g": 7.0, "$": 101}, {"g": 14.0, "$": 202}, {"g": 28.0, "$": 381}]}, {"i": "0c721ae1", "w": "D", "u": "15-night-walker-emerald-cannabis", "s": "tokyo-starfish-923-se-3rd-street", "m": "R", "a": "923 SE 3rd St Bend, OR", "b": "Emerald Cannabis", "n": "$15 - Night Walker - Emerald Cannabis", "t": "I", "p": "flower-stock-8-v1.jpg", "%": 28.4, "cbd": 0, "tac": 0, "c": [{"g": 1.0, "$": 15}, {"g": 2.0, "$": 30}, {"g": 3.5, "$": 50}, {"g": 7.0, "$": 95}, {"g": 14.0, "$": 190}, {"g": 28.0, "$": 357}]}, {"i": "6e8b990f", "w": "D", "u": "7-tokyo-runtz", "s": "tokyo-starfish-923-se-3rd-street", "m": "R", "a": "923 SE 3rd St Bend, OR", "b": "Tokyo Starfish", "n": "$7 - Tokyo - Runtz", "t": "H", "p": "b9d1c87b74de75385021df92173c97a1", "%": 18.9, "cbd": 0, "tac": 0, "c": [{"g": 1.0, "$": 7}, {"g": 2.0, "$": 14}, {"g": 3.5, "$": 23}, {"g": 7.0, "$": 44}, {"g": 14.0, "$": 88}, {"g": 28.0, "$": 167}]}, {"i": "d5b05a51", "w": "D", "u": "6-orange-bubblegum-alter", "s": "tokyo-starfish-923-se-3rd-street", "m": "R", "a": "923 SE 3rd St Bend, OR", "b": "Alter Farms", "n": "$6 - Orange Bubblegum - Alter", "t": "S", "p": "d0685184f9766f24de9bf6ccf8e7223e", "%": 23.0, "cbd": 0, "tac": 0, "c": [{"g": 1.0, "$": 6}, {"g": 2.0, "$": 12}, {"g": 3.5, "$": 20}, {"g": 7.0, "$": 38}, {"g": 14.0, "$": 76}, {"g": 28.0, "$": 143}]}, {"i": "8895df08", "w": "D", "u": "9-bike-lights-arise-cannabis", "s": "tokyo-starfish-923-se-3rd-street", "m": "R", "a": "923 SE 3rd St Bend, OR", "b": "Arise Cannabis", "n": "$9 - Bike Lights - Arise Cannabis", "t": "H", "p": "8ed4ba85704c60ae08e8089210b6eaca", "%": 26.6, "cbd": 0, "tac": 0, "c": [{"g": 1.0, "$": 9}, {"g": 2.0, "$": 18}]}, {"i": "3ff561f8", "w": "D", "u": "10-tokyo-greazy-runtz", "s": "tokyo-starfish-923-se-3rd-street", "m": "R", "a": "923 SE 3rd St Bend, OR", "b": "Tokyo Starfish", "n": "$10 - Tokyo - Greazy Runtz", "t": "H", "p": "f7dd5cc58f0eecaaedaa3727e98621c8", "%": 22.8, "cbd": 0.1, "tac": 0, "c": [{"g": 1.0, "$": 10}, {"g": 2.0, "$": 20}, {"g": 3.5, "$": 33}, {"g": 7.0, "$": 63}, {"g": 14.0, "$": 126}, {"g": 28.0, "$": 238}]}, {"i": "05c17b81", "w": "D", "u": "pre-pack-tokyo-purple-ice-water", "s": "tokyo-starfish-923-se-3rd-street", "m": "R", "a": "923 SE 3rd St Bend, OR", "b": "TG Industries", "n": "Pre Pack - Tokyo - Purple Ice Water", "t": "H", "p": "flower-stock-10-v1.jpg", "%": 0, "cbd": 0, "tac": 0, "c": [{"g": 28.0, "$": 100}]}, {"i": "7fc07846", "w": "D", "u": "10-tokyo-durban-poison", "s": "tokyo-starfish-923-se-3rd-street", "m": "R", "a": "923 SE 3rd St Bend, OR", "b": "Tokyo Starfish", "n": "$10 - Tokyo - Durban Poison", "t": "S", "p": "5f328986d4726016e8ae930ae88c472f", "%": 23.5, "cbd": 0, "tac": 0, "c": [{"g": 1.0, "$": 10}, {"g": 2.0, "$": 20}, {"g": 3.5, "$": 33}, {"g": 7.0, "$": 63}, {"g": 14.0, "$": 126}, {"g": 28.0, "$": 238}]}, {"i": "6310eb2e", "w": "D", "u": "10-ice-cream-man-earl-baker", "s": "tokyo-starfish-923-se-3rd-street", "m": "R", "a": "923 SE 3rd St Bend, OR", "b": "Earl Baker", "n": "$10 - Ice Cream Man - Earl Baker", "t": "H", "p": "flower-stock-4-v1.jpg", "%": 25.5, "cbd": 0.1, "tac": 0, "c": [{"g": 1.0, "$": 10}, {"g": 2.0, "$": 20}, {"g": 3.5, "$": 33}, {"g": 7.0, "$": 63}, {"g": 14.0, "$": 126}, {"g": 28.0, "$": 238}]}, {"i": "b8d6c60f", "w": "D", "u": "8-tokyo-island-freeze", "s": "tokyo-starfish-923-se-3rd-street", "m": "R", "a": "923 SE 3rd St Bend, OR", "b": "Tokyo Starfish", "n": "$8 - Tokyo - Island Freeze", "t": "H", "p": "707789971e95e7b8bade6662516710b8", "%": 22.4, "cbd": 0, "tac": 0, "c": [{"g": 1.0, "$": 8}, {"g": 2.0, "$": 16}, {"g": 3.5, "$": 27}, {"g": 7.0, "$": 50}, {"g": 14.0, "$": 100}, {"g": 28.0, "$": 190}]}, {"i": "17b2506c", "w": "D", "u": "alter-space-jogger-party-pouch", "s": "tokyo-starfish-923-se-3rd-street", "m": "R", "a": "923 SE 3rd St Bend, OR", "b": "Alter Farms", "n": "Alter - Space Jogger Party Pouch", "t": "I", "p": "d0685184f9766f24de9bf6ccf8e7223e", "%": 22.8, "cbd": 0.1, "tac": 0, "c": [{"g": 28.0, "$": 96}]}, {"i": "b6c39e64", "w": "D", "u": "6-turquoise-jeep-golden-jackal", "s": "tokyo-starfish-923-se-3rd-street", "m": "R", "a": "923 SE 3rd St Bend, OR", "b": "Golden Jackal Farm", "n": "$6 - Turquoise Jeep - Golden Jackal", "t": "H", "p": "flower-stock-2-v1.jpg", "%": 26.8, "cbd": 0, "tac": 0, "c": [{"g": 1.0, "$": 6}, {"g": 2.0, "$": 12}, {"g": 3.5, "$": 20}, {"g": 7.0, "$": 38}, {"g": 14.0, "$": 76}, {"g": 28.0, "$": 143}]}, {"i": "f1bf1539", "w": "D", "u": "14-taste-the-rainbow-virgin-leaf", "s": "tokyo-starfish-923-se-3rd-street", "m": "R", "a": "923 SE 3rd St Bend, OR", "b": "Virgin Cannabis", "n": "$14 - Taste The Rainbow - Virgin Leaf", "t": "S", "p": "4836e5d13fa785bad16df7c2f291095b", "%": 26.9, "cbd": 0, "tac": 0, "c": [{"g": 1.0, "$": 14}, {"g": 2.0, "$": 28}, {"g": 3.5, "$": 47}, {"g": 7.0, "$": 88}, {"g": 14.0, "$": 176}, {"g": 28.0, "$": 333}]}, {"i": "db60529d", "w": "D", "u": "15-the-bizz-koru-cannabis", "s": "tokyo-starfish-923-se-3rd-street", "m": "R", "a": "923 SE 3rd St Bend, OR", "b": "Koru Cannabis", "n": "$15 - The Bizz - Koru Cannabis", "t": "S", "p": "0d76b102873b8ad4ae7f72f45da9f3f0", "%": 28.5, "cbd": 0, "tac": 0, "c": [{"g": 1.0, "$": 15}, {"g": 2.0, "$": 30}]}, {"i": "98ae0e02", "w": "D", "u": "9-tokyo-terple", "s": "tokyo-starfish-923-se-3rd-street", "m": "R", "a": "923 SE 3rd St Bend, OR", "b": "Tokyo Starfish", "n": "$9 - Tokyo - Terple", "t": "H", "p": "9a8620aedf71eb84d8983a992cebf9a7", "%": 23.1, "cbd": 0, "tac": 0, "c": [{"g": 1.0, "$": 9}, {"g": 2.0, "$": 18}, {"g": 3.5, "$": 30}, {"g": 7.0, "$": 57}, {"g": 14.0, "$": 114}, {"g": 28.0, "$": 214}]}, {"i": "2e4e6040", "w": "D", "u": "5-golden-sunset-roganja", "s": "tokyo-starfish-923-se-3rd-street", "m": "R", "a": "923 SE 3rd St Bend, OR", "b": "Massive Roganja", "n": "$5 - Golden Sunset - Roganja", "t": "H", "p": "flower-stock-1-v1.jpg", "%": 25.4, "cbd": 0.1, "tac": 0, "c": [{"g": 1.0, "$": 5}, {"g": 2.0, "$": 10}, {"g": 3.5, "$": 17}, {"g": 7.0, "$": 32}, {"g": 14.0, "$": 64}, {"g": 28.0, "$": 119}]}, {"i": "239cbca2", "w": "D", "u": "12-tokyo-strawberry-guava", "s": "tokyo-starfish-923-se-3rd-street", "m": "R", "a": "923 SE 3rd St Bend, OR", "b": "Tokyo", "n": "$12 - Tokyo - Strawberry Guava", "t": "S", "p": "5fbd8b206f2541dd5872497f0ed80706", "%": 25.7, "cbd": 0.1, "tac": 0, "c": [{"g": 1.0, "$": 12}, {"g": 2.0, "$": 24}, {"g": 3.5, "$": 40}, {"g": 7.0, "$": 76}, {"g": 14.0, "$": 152}, {"g": 28.0, "$": 286}]}, {"i": "575414ee", "w": "D", "u": "11-tokyo-chem-chillz", "s": "tokyo-starfish-923-se-3rd-street", "m": "R", "a": "923 SE 3rd St Bend, OR", "b": "Tokyo Starfish", "n": "$11 - Tokyo - Chem Chillz", "t": "I", "p": "b9d1c87b74de75385021df92173c97a1", "%": 25.7, "cbd": 0.1, "tac": 0, "c": [{"g": 1.0, "$": 11}, {"g": 2.0, "$": 22}, {"g": 3.5, "$": 37}, {"g": 7.0, "$": 69}, {"g": 14.0, "$": 138}, {"g": 28.0, "$": 262}]}, {"i": "bab23ce0", "w": "D", "u": "10-tokyo-donkey-butter", "s": "tokyo-starfish-923-se-3rd-street", "m": "R", "a": "923 SE 3rd St Bend, OR", "b": "Tokyo Starfish", "n": "$10 - Tokyo - Donkey Butter", "t": "I", "p": "8e230e92f72d5e2f3fed264aceb41fba", "%": 19.7, "cbd": 0, "tac": 0, "c": [{"g": 1.0, "$": 10}, {"g": 2.0, "$": 20}, {"g": 3.5, "$": 33}, {"g": 7.0, "$": 63}, {"g": 14.0, "$": 126}, {"g": 28.0, "$": 238}]}, {"i": "52053ecc", "w": "D", "u": "12-grape-pie-frontier-farms", "s": "tokyo-starfish-923-se-3rd-street", "m": "R", "a": "923 SE 3rd St Bend, OR", "b": "Frontier Farms", "n": "$12 - Grape Pie - Frontier Farms", "t": "H", "p": "b8987586b6c1aaff9b6b8780a47d192a", "%": 27.2, "cbd": 0, "tac": 0, "c": [{"g": 1.0, "$": 12}, {"g": 2.0, "$": 24}, {"g": 3.5, "$": 40}, {"g": 7.0, "$": 76}, {"g": 14.0, "$": 152}, {"g": 28.0, "$": 286}]}, {"i": "ee580e8a", "w": "D", "u": "superstitious", "s": "tokyo-starfish-923-se-3rd-street", "m": "R", "a": "923 SE 3rd St Bend, OR", "b": "Alter Farms", "n": "Superstitious", "t": "S", "p": "c916a057be8eb289d866ba3dc9e30f82", "%": 20.9, "cbd": 0.1, "tac": 0, "c": [{"g": 28.0, "$": 96}]}, {"i": "45efa595", "w": "D", "u": "8-blue-dream-grown-rogue", "s": "tokyo-starfish-923-se-3rd-street", "m": "R", "a": "923 SE 3rd St Bend, OR", "b": "Grown Rogue", "n": "$8 - Blue Dream - Grown Rogue", "t": "H", "p": "9ccc9639c61b84ca8602293e08ebb179", "%": 27.6, "cbd": 0, "tac": 0, "c": [{"g": 1.0, "$": 8}, {"g": 2.0, "$": 16}, {"g": 3.5, "$": 27}, {"g": 7.0, "$": 50}, {"g": 14.0, "$": 100}, {"g": 28.0, "$": 190}]}, {"i": "df3d4d57", "w": "D", "u": "grease-monkey-22253", "s": "tokyo-starfish-923-se-3rd-street", "m": "R", "a": "923 SE 3rd St Bend, OR", "b": "Summary", "n": "Grease Monkey", "t": "I", "p": "b1313f480b75ba8a12ff65d67b858c2e", "%": 27.0, "cbd": 0, "tac": 0, "c": [{"g": 1.0, "$": 12}, {"g": 2.0, "$": 24}, {"g": 3.5, "$": 40}, {"g": 7.0, "$": 76}, {"g": 14.0, "$": 152}, {"g": 28.0, "$": 286}]}, {"i": "7b20b189", "w": "D", "u": "9-tropicanna-kookies-5-pioneer", "s": "tokyo-starfish-923-se-3rd-street", "m": "R", "a": "923 SE 3rd St Bend, OR", "b": "Pioneer", "n": "$9 -  Tropicanna Kookies #5 - Pioneer", "t": "I", "p": "flower-stock-11-v1.jpg", "%": 0, "cbd": 0, "tac": 0, "c": []}, {"i": "21f6bf61", "w": "D", "u": "10-las-vegas-og-zion-roots", "s": "tokyo-starfish-923-se-3rd-street", "m": "R", "a": "923 SE 3rd St Bend, OR", "b": "Zion Roots", "n": "$10 - Las Vegas OG - Zion Roots", "t": "S", "p": "flower-stock-4-v1.jpg", "%": 29.0, "cbd": 0, "tac": 0, "c": [{"g": 1.0, "$": 10}, {"g": 2.0, "$": 20}, {"g": 3.5, "$": 33}, {"g": 7.0, "$": 63}, {"g": 14.0, "$": 126}, {"g": 28.0, "$": 238}]}, {"i": "4c971bb9", "w": "D", "u": "7-jack-herer-grown-rogue", "s": "tokyo-starfish-923-se-3rd-street", "m": "R", "a": "923 SE 3rd St Bend, OR", "b": "Grown Rogue", "n": "$7 - Jack Herer - Grown Rogue", "t": "S", "p": "9ccc9639c61b84ca8602293e08ebb179", "%": 22.3, "cbd": 0, "tac": 0, "c": [{"g": 1.0, "$": 7}, {"g": 2.0, "$": 14}, {"g": 3.5, "$": 23}, {"g": 7.0, "$": 44}, {"g": 14.0, "$": 88}, {"g": 28.0, "$": 167}]}]